MANIFEST.in
README.txt
setup.py
c2/__init__.py
c2.app.issuelink.egg-info/PKG-INFO
c2.app.issuelink.egg-info/SOURCES.txt
c2.app.issuelink.egg-info/dependency_links.txt
c2.app.issuelink.egg-info/entry_points.txt
c2.app.issuelink.egg-info/namespace_packages.txt
c2.app.issuelink.egg-info/not-zip-safe
c2.app.issuelink.egg-info/requires.txt
c2.app.issuelink.egg-info/top_level.txt
c2/app/__init__.py
c2/app/issuelink/__init__.py
c2/app/issuelink/addinglink.py
c2/app/issuelink/configure.zcml
c2/app/issuelink/tests.py
c2/app/issuelink/version.txt
c2/app/issuelink/controlpanel/__init__.py
c2/app/issuelink/controlpanel/config.py
c2/app/issuelink/controlpanel/configlet.py
c2/app/issuelink/controlpanel/configure.zcml
c2/app/issuelink/controlpanel/exportimport.py
c2/app/issuelink/controlpanel/interfaces.py
c2/app/issuelink/profiles/default/componentregistry.xml
c2/app/issuelink/profiles/default/controlpanel.xml
c2/app/issuelink/profiles/default/issuelink.xml
c2/app/issuelink/profiles/default/metadata.xml
docs/HISTORY.txt
docs/INSTALL.txt
docs/LICENSE.GPL
docs/LICENSE.txt