Metadata-Version: 1.0
Name: c2.app.issuelink
Version: 1.0b1
Summary: This product is auto link for issue number in Plone page
Home-page: http://www.cmscom.jp
Author: Manabu TERADA
Author-email: terada@cmscom.jp
License: GPL
Keywords: plone issue trac
Platform: UNKNOWN
Classifier: Framework :: Plone
Classifier: Programming Language :: Python
